[
    {
        "anonymous": false,
        "inputs": [
            {
                "indexed": false,
                "internalType": "uint256",
                "name": "oldFee",
                "type": "uint256"
            },
            {
                "indexed": false,
                "internalType": "uint256",
                "name": "newFee",
                "type": "uint256"
            }
        ],
        "name": "FeeUpdated",
        "type": "event"
    },
    {
        "anonymous": false,
        "inputs": [
            {
                "indexed": true,
                "internalType": "address",
                "name": "oldAddress",
                "type": "address"
            },
            {
                "indexed": true,
                "internalType": "address",
                "name": "newAddress",
                "type": "address"
            }
        ],
        "name": "MasterAggregatorUpdated",
        "type": "event"
    },
    {
        "anonymous": false,
        "inputs": [
            {
                "indexed": true,
                "internalType": "address",
                "name": "previousOwner",
                "type": "address"
            },
            {
                "indexed": true,
                "internalType": "address",
                "name": "newOwner",
                "type": "address"
            }
        ],
        "name": "OwnershipTransferred",
        "type": "event"
    },
    {
        "anonymous": false,
        "inputs": [
            {
                "indexed": true,
                "internalType": "address",
                "name": "carbonPool",
                "type": "address"
            },
            {
                "indexed": true,
                "internalType": "address",
                "name": "poolRouter",
                "type": "address"
            }
        ],
        "name": "PoolAdded",
        "type": "event"
    },
    {
        "anonymous": false,
        "inputs": [
            {
                "indexed": true,
                "internalType": "address",
                "name": "carbonPool",
                "type": "address"
            }
        ],
        "name": "PoolRemoved",
        "type": "event"
    },
    {
        "anonymous": false,
        "inputs": [
            {
                "indexed": true,
                "internalType": "address",
                "name": "carbonPool",
                "type": "address"
            },
            {
                "indexed": true,
                "internalType": "address",
                "name": "oldRouter",
                "type": "address"
            },
            {
                "indexed": true,
                "internalType": "address",
                "name": "newRouter",
                "type": "address"
            }
        ],
        "name": "PoolRouterChanged",
        "type": "event"
    },
    {
        "anonymous": false,
        "inputs": [
            {
                "indexed": true,
                "internalType": "address",
                "name": "retiringAddress",
                "type": "address"
            },
            {
                "indexed": true,
                "internalType": "address",
                "name": "beneficiaryAddress",
                "type": "address"
            },
            {
                "indexed": false,
                "internalType": "string",
                "name": "beneficiaryString",
                "type": "string"
            },
            {
                "indexed": false,
                "internalType": "string",
                "name": "retirementMessage",
                "type": "string"
            },
            {
                "indexed": true,
                "internalType": "address",
                "name": "carbonPool",
                "type": "address"
            },
            {
                "indexed": false,
                "internalType": "address",
                "name": "carbonToken",
                "type": "address"
            },
            {
                "indexed": false,
                "internalType": "uint256",
                "name": "retiredAmount",
                "type": "uint256"
            }
        ],
        "name": "ToucanRetired",
        "type": "event"
    },
    {
        "inputs": [
            {
                "internalType": "address",
                "name": "_poolToken",
                "type": "address"
            },
            {
                "internalType": "address",
                "name": "_router",
                "type": "address"
            }
        ],
        "name": "addPool",
        "outputs": [
            {
                "internalType": "bool",
                "name": "",
                "type": "bool"
            }
        ],
        "stateMutability": "nonpayable",
        "type": "function"
    },
    {
        "inputs": [],
        "name": "feeAmount",
        "outputs": [
            {
                "internalType": "uint256",
                "name": "",
                "type": "uint256"
            }
        ],
        "stateMutability": "view",
        "type": "function"
    },
    {
        "inputs": [
            {
                "internalType": "address",
                "name": "_token",
                "type": "address"
            },
            {
                "internalType": "address",
                "name": "_recipient",
                "type": "address"
            }
        ],
        "name": "feeWithdraw",
        "outputs": [
            {
                "internalType": "bool",
                "name": "",
                "type": "bool"
            }
        ],
        "stateMutability": "nonpayable",
        "type": "function"
    },
    {
        "inputs": [
            {
                "internalType": "address",
                "name": "_sourceToken",
                "type": "address"
            },
            {
                "internalType": "address",
                "name": "_poolToken",
                "type": "address"
            },
            {
                "internalType": "uint256",
                "name": "_poolAmount",
                "type": "uint256"
            }
        ],
        "name": "getNeededBuyAmount",
        "outputs": [
            {
                "internalType": "uint256",
                "name": "",
                "type": "uint256"
            },
            {
                "internalType": "uint256",
                "name": "",
                "type": "uint256"
            }
        ],
        "stateMutability": "view",
        "type": "function"
    },
    {
        "inputs": [
            {
                "internalType": "address",
                "name": "_sourceToken",
                "type": "address"
            },
            {
                "internalType": "address",
                "name": "_poolToken",
                "type": "address"
            }
        ],
        "name": "getSwapPath",
        "outputs": [
            {
                "internalType": "address[]",
                "name": "",
                "type": "address[]"
            }
        ],
        "stateMutability": "view",
        "type": "function"
    },
    {
        "inputs": [],
        "name": "initialize",
        "outputs": [],
        "stateMutability": "nonpayable",
        "type": "function"
    },
    {
        "inputs": [
            {
                "internalType": "address",
                "name": "",
                "type": "address"
            }
        ],
        "name": "isPoolToken",
        "outputs": [
            {
                "internalType": "bool",
                "name": "",
                "type": "bool"
            }
        ],
        "stateMutability": "view",
        "type": "function"
    },
    {
        "inputs": [],
        "name": "masterAggregator",
        "outputs": [
            {
                "internalType": "address",
                "name": "",
                "type": "address"
            }
        ],
        "stateMutability": "view",
        "type": "function"
    },
    {
        "inputs": [],
        "name": "owner",
        "outputs": [
            {
                "internalType": "address",
                "name": "",
                "type": "address"
            }
        ],
        "stateMutability": "view",
        "type": "function"
    },
    {
        "inputs": [
            {
                "internalType": "address",
                "name": "",
                "type": "address"
            }
        ],
        "name": "poolRouter",
        "outputs": [
            {
                "internalType": "address",
                "name": "",
                "type": "address"
            }
        ],
        "stateMutability": "view",
        "type": "function"
    },
    {
        "inputs": [
            {
                "internalType": "address",
                "name": "_poolToken",
                "type": "address"
            }
        ],
        "name": "removePool",
        "outputs": [
            {
                "internalType": "bool",
                "name": "",
                "type": "bool"
            }
        ],
        "stateMutability": "nonpayable",
        "type": "function"
    },
    {
        "inputs": [],
        "name": "renounceOwnership",
        "outputs": [],
        "stateMutability": "nonpayable",
        "type": "function"
    },
    {
        "inputs": [
            {
                "internalType": "address",
                "name": "_sourceToken",
                "type": "address"
            },
            {
                "internalType": "address",
                "name": "_poolToken",
                "type": "address"
            },
            {
                "internalType": "uint256",
                "name": "_amount",
                "type": "uint256"
            },
            {
                "internalType": "bool",
                "name": "_amountInCarbon",
                "type": "bool"
            },
            {
                "internalType": "address",
                "name": "_beneficiaryAddress",
                "type": "address"
            },
            {
                "internalType": "string",
                "name": "_beneficiaryString",
                "type": "string"
            },
            {
                "internalType": "string",
                "name": "_retirementMessage",
                "type": "string"
            },
            {
                "internalType": "address",
                "name": "_retiree",
                "type": "address"
            }
        ],
        "name": "retireToucan",
        "outputs": [],
        "stateMutability": "nonpayable",
        "type": "function"
    },
    {
        "inputs": [
            {
                "internalType": "uint256",
                "name": "_amount",
                "type": "uint256"
            }
        ],
        "name": "setFeeAmount",
        "outputs": [
            {
                "internalType": "bool",
                "name": "",
                "type": "bool"
            }
        ],
        "stateMutability": "nonpayable",
        "type": "function"
    },
    {
        "inputs": [
            {
                "internalType": "address",
                "name": "_newAddress",
                "type": "address"
            }
        ],
        "name": "setMasterAggregator",
        "outputs": [
            {
                "internalType": "bool",
                "name": "",
                "type": "bool"
            }
        ],
        "stateMutability": "nonpayable",
        "type": "function"
    },
    {
        "inputs": [
            {
                "internalType": "address",
                "name": "_poolToken",
                "type": "address"
            },
            {
                "internalType": "address",
                "name": "_router",
                "type": "address"
            }
        ],
        "name": "setPoolRouter",
        "outputs": [
            {
                "internalType": "bool",
                "name": "",
                "type": "bool"
            }
        ],
        "stateMutability": "nonpayable",
        "type": "function"
    },
    {
        "inputs": [
            {
                "internalType": "address",
                "name": "newOwner",
                "type": "address"
            }
        ],
        "name": "transferOwnership",
        "outputs": [],
        "stateMutability": "nonpayable",
        "type": "function"
    }
]
